setup.cfg
setup.py
Products/__init__.py
Products.ECQuiz.egg-info/PKG-INFO
Products.ECQuiz.egg-info/SOURCES.txt
Products.ECQuiz.egg-info/dependency_links.txt
Products.ECQuiz.egg-info/entry_points.txt
Products.ECQuiz.egg-info/namespace_packages.txt
Products.ECQuiz.egg-info/not-zip-safe
Products.ECQuiz.egg-info/requires.txt
Products.ECQuiz.egg-info/top_level.txt
Products/ECQuiz/CHANGES.txt
Products/ECQuiz/COPYING
Products/ECQuiz/ECQAbstractGroup.py
Products/ECQuiz/ECQFolder.py
Products/ECQuiz/ECQGroup.py
Products/ECQuiz/ECQReference.py
Products/ECQuiz/ECQResult.py
Products/ECQuiz/ECQTool.py
Products/ECQuiz/ECQuiz.py
Products/ECQuiz/InlineTextField.py
Products/ECQuiz/ListValidator.py
Products/ECQuiz/README.txt
Products/ECQuiz/Statistics.py
Products/ECQuiz/TODO.txt
Products/ECQuiz/__init__.py
Products/ECQuiz/config.py
Products/ECQuiz/configure.zcml
Products/ECQuiz/ec_tool.png
Products/ECQuiz/findUntranslatedMessages.py
Products/ECQuiz/l2.py
Products/ECQuiz/permissions.py
Products/ECQuiz/permissions.zcml
Products/ECQuiz/profiles.zcml
Products/ECQuiz/qti.py
Products/ECQuiz/refresh.txt
Products/ECQuiz/setuphandlers.py
Products/ECQuiz/sharing.py
Products/ECQuiz/tools.py
Products/ECQuiz/validators.py
Products/ECQuiz/version.txt
Products/ECQuiz/wikitool.py
Products/ECQuiz/AnswerTypes/ECQBaseAnswer.py
Products/ECQuiz/AnswerTypes/ECQCorrectAnswer.py
Products/ECQuiz/AnswerTypes/ECQMCAnswer.py
Products/ECQuiz/AnswerTypes/ECQScaleAnswer.py
Products/ECQuiz/AnswerTypes/ECQSelectionAnswer.py
Products/ECQuiz/AnswerTypes/__init__.py
Products/ECQuiz/QuestionTypes/ECQBaseQuestion.py
Products/ECQuiz/QuestionTypes/ECQExtendedTextQuestion.py
Products/ECQuiz/QuestionTypes/ECQMCQuestion.py
Products/ECQuiz/QuestionTypes/ECQPointsQuestion.py
Products/ECQuiz/QuestionTypes/ECQRatingQuestion.py
Products/ECQuiz/QuestionTypes/ECQScaleQuestion.py
Products/ECQuiz/QuestionTypes/ECQSelectionQuestion.py
Products/ECQuiz/QuestionTypes/__init__.py
Products/ECQuiz/i18n/ECQuiz-de.po
Products/ECQuiz/i18n/ECQuiz-en.po
Products/ECQuiz/i18n/ECQuiz-fr.po
Products/ECQuiz/i18n/ECQuiz-it.po
Products/ECQuiz/i18n/ECQuiz-sl.po
Products/ECQuiz/i18n/ECQuiz.pot
Products/ECQuiz/i18n/plone-de.po
Products/ECQuiz/i18n/plone-en.po
Products/ECQuiz/i18n/plone-fr.po
Products/ECQuiz/i18n/plone-it.po
Products/ECQuiz/i18n/plone-sl.po
