Metadata-Version: 1.0
Name: Products.ECQuiz
Version: 1.4-rc1
Summary: Create and deliver multiple-choice tests.
Home-page: http://plone.org/products/ecquiz/
Author: Wolfram Fenske and Michael Piotrowski and Mario Amelung
Author-email: wfenske@eudemonia-soltions.de and mxp@dynalabs.de and mario.amelung@gmx.de
License: GPL
Platform: UNKNOWN
Classifier: Framework :: Plone
Classifier: Framework :: Zope2
Classifier: Programming Language :: Python
Classifier: Topic :: Software Development :: Libraries :: Python Modules
